INSTALL
LICENSE
MANIFEST.in
README.md
SIGNING_KEYS.pub
alt-requirements.txt
pyproject.toml
setup.cfg
setup.py
xmr-requirements.txt
cmds/mmgen-addrgen
cmds/mmgen-addrimport
cmds/mmgen-autosign
cmds/mmgen-cli
cmds/mmgen-keygen
cmds/mmgen-msg
cmds/mmgen-passchg
cmds/mmgen-passgen
cmds/mmgen-regtest
cmds/mmgen-seedjoin
cmds/mmgen-seedsplit
cmds/mmgen-subwalletgen
cmds/mmgen-swaptxcreate
cmds/mmgen-swaptxdo
cmds/mmgen-tool
cmds/mmgen-txbump
cmds/mmgen-txcreate
cmds/mmgen-txdo
cmds/mmgen-txsend
cmds/mmgen-txsign
cmds/mmgen-walletchk
cmds/mmgen-walletconv
cmds/mmgen-walletgen
cmds/mmgen-xmrwallet
doc/release-notes/release-notes-v0.10.0.md
doc/release-notes/release-notes-v0.11.0.md
doc/release-notes/release-notes-v0.12.0.md
doc/release-notes/release-notes-v0.12.1.md
doc/release-notes/release-notes-v0.8.3.md
doc/release-notes/release-notes-v0.8.5.md
doc/release-notes/release-notes-v0.8.6.md
doc/release-notes/release-notes-v0.8.7.md
doc/release-notes/release-notes-v0.8.8.md
doc/release-notes/release-notes-v0.8.9.md
doc/release-notes/release-notes-v0.9.0.md
doc/release-notes/release-notes-v0.9.1.md
doc/release-notes/release-notes-v0.9.3.md
doc/release-notes/release-notes-v0.9.5.md
doc/release-notes/release-notes-v0.9.6.md
doc/release-notes/release-notes-v0.9.7.md
doc/release-notes/release-notes-v0.9.8.md
doc/release-notes/release-notes-v0.9.9.md
doc/release-notes/release-notes-v0.9.9a.md
doc/release-notes/release-notes-v13.0.0.md
doc/release-notes/release-notes-v13.0.1.md
doc/release-notes/release-notes-v13.0.2.md
doc/release-notes/release-notes-v13.1.0.md
doc/release-notes/release-notes-v13.2.0.md
doc/release-notes/release-notes-v13.3.0.md
doc/release-notes/release-notes-v14.0.0.md
doc/release-notes/release-notes-v14.1.0.md
doc/release-notes/release-notes-v15.0.0.md
doc/release-notes/release-notes-v16.0.0.md
doc/wiki/cmds/command-help-addrgen.md
doc/wiki/cmds/command-help-addrimport.md
doc/wiki/cmds/command-help-autosign.md
doc/wiki/cmds/command-help-cli.md
mmgen_wallet.egg-info/PKG-INFO
mmgen_wallet.egg-info/SOURCES.txt
mmgen_wallet.egg-info/dependency_links.txt
mmgen_wallet.egg-info/requires.txt
mmgen_wallet.egg-info/top_level.txt
