Metadata-Version: 2.4
Name: mmgen-wallet
Version: 16.0.0
Summary: MMGen cryptocurrency wallet suite
Home-page: https://github.com/mmgen/mmgen-wallet
Author: The MMGen Project
Author-email: mmgen@tuta.io
License: GNU GPL v3
Project-URL: Website, https://mmgen-wallet.cc
Project-URL: Repository, https://github.com/mmgen/mmgen-wallet.git
Project-URL: Documentation, https://github.com/mmgen/mmgen-wallet/wiki
Project-URL: Changelog, https://github.com/mmgen/mmgen-wallet/commits/master
Project-URL: Download, https://github.com/mmgen/mmgen-wallet/releases
Project-URL: Issues, https://github.com/mmgen/mmgen-wallet/issues
Project-URL: Github, https://github.com/mmgen/mmgen-wallet
Project-URL: Gitlab, https://gitlab.com/mmgen/mmgen-wallet
Project-URL: Reddit, https://www.reddit.com/user/mmgen-py
Project-URL: Twitter, https://x.com/TheMMGenProject
Project-URL: Keybase, https://keybase.io/mmgen
Keywords: file: mmgen/data/keywords
Platform: Linux
Platform: Armbian
Platform: Raspbian
Platform: MS Windows
Platform: MacOS
Classifier: Operating System :: POSIX :: Linux
Classifier: Operating System :: Microsoft :: Windows
Classifier: Operating System :: MacOS
Classifier: Environment :: Console
Classifier: Programming Language :: Python :: 3
Classifier: Programming Language :: C
Classifier: Framework :: AsyncIO
Classifier: Framework :: aiohttp
Classifier: Topic :: Office/Business :: Financial
Classifier: Topic :: Security :: Cryptography
Classifier: Topic :: Software Development :: Libraries :: Python Modules
Classifier: Topic :: Utilities
Classifier: Topic :: Software Development :: User Interfaces
Classifier: Topic :: Software Development :: Testing
Classifier: Topic :: Software Development :: Testing :: Mocking
Classifier: Topic :: Software Development :: Testing :: Unit
Classifier: Intended Audience :: Developers
Classifier: Intended Audience :: End Users/Desktop
Classifier: Intended Audience :: Financial and Insurance Industry
Classifier: Intended Audience :: System Administrators
Classifier: Development Status :: 5 - Production/Stable
Requires-Python: >=3.9
License-File: LICENSE
Requires-Dist: gmpy2
Requires-Dist: cryptography
Requires-Dist: pynacl
Requires-Dist: ecdsa
Requires-Dist: aiohttp==3.12.9
Requires-Dist: requests
Requires-Dist: pexpect
Requires-Dist: lxml
Requires-Dist: scrypt
Requires-Dist: semantic-version; platform_system != "Windows"
Dynamic: license-file
